ClassifyGene/Classify.py
ClassifyGene/__init__.py
ClassifyGene-1.0.0.dist-info/METADATA
ClassifyGene-1.0.0.dist-info/RECORD
ClassifyGene-1.0.0.dist-info/WHEEL
ClassifyGene-1.0.0.dist-info/top_level.txt
